<?xml version="1.0"?>
<PagePortable xmlns:xsd="http://www.w3.org/2001/XMLSchema" xmlns:xsi="http://www.w3.org/2001/XMLSchema-instance">
  <Title>Gerador de cubos - Cubos</Title>
  <Url>~/aga/a/f/aga_t2292_at3017_hsa8244ff2.aspx</Url>
  <AutoGenerated>true</AutoGenerated>
  <EntityPermissionId />
  <TemplateId />
  <Details />
  <Id>ADM_CUBOS__CUBOS_FORM</Id>
  <Level>Benner</Level>
  <CodeFile />
  <CodeInherits />
  <Widgets>
    <PageWidgetPortable>
      <Id>FORMULARIO</Id>
      <Title>Gerador de cubos - Cubos</Title>
      <Order>1</Order>
      <ShowTitle>true</ShowTitle>
      <PortletCssClass />
      <FontIcon />
      <Subtitle />
      <ChromeState>Normal</ChromeState>
      <PortletLayout>Default</PortletLayout>
      <WidgetTypeId>AjaxForm</WidgetTypeId>
      <BootstrapCols>12</BootstrapCols>
      <XmlAttributes><![CDATA[<AjaxFormAttributes>
  <EntityViewName>AGA_Z_CUBOS.FORM</EntityViewName>
  <CanDelete>true</CanDelete>
  <CanUpdate>true</CanUpdate>
  <CanInsert>true</CanInsert>
  <IncludeRecordInRecentItems>true</IncludeRecordInRecentItems>
  <UserDefinedCriteriaWhereClause>'forcar_carga_form'='forcar_carga_form'</UserDefinedCriteriaWhereClause>
  <UserDefinedCommandsVisible>true</UserDefinedCommandsVisible>
</AjaxFormAttributes>]]></XmlAttributes>
      <Level>Benner</Level>
    </PageWidgetPortable>
    <PageWidgetPortable>
      <Id>WIDGET_3587</Id>
      <MasterWidgetId>FORMULARIO</MasterWidgetId>
      <Title>Gerações</Title>
      <Order>10</Order>
      <ShowTitle>false</ShowTitle>
      <PortletCssClass />
      <FontIcon />
      <Subtitle />
      <ChromeState>Normal</ChromeState>
      <PortletLayout>Default</PortletLayout>
      <WidgetTypeId>SimpleGrid</WidgetTypeId>
      <BootstrapCols>12</BootstrapCols>
      <XmlAttributes><![CDATA[<SimpleGridAttributes>
  <EntityViewName>AGA_Z_CUBOGERACOES.GRID</EntityViewName>
  <CanDelete>true</CanDelete>
  <CanUpdate>false</CanUpdate>
  <CanInsert>false</CanInsert>
  <Mode>1</Mode>
  <UserDefinedSelectColumnVisible>false</UserDefinedSelectColumnVisible>
  <UserDefinedPageSize>10</UserDefinedPageSize>
  <SystemFilterOnly>false</SystemFilterOnly>
  <DisplayRowCommand>true</DisplayRowCommand>
  <CompanyFilterMode>2</CompanyFilterMode>
  <UserDefinedCriteriaWhereClause>(A.CUBO IN(SELECT AA.HANDLE FROM Z_CUBOS AA WHERE AA.ACESSORESTRITO = 'N') OR (A.CUBO IN (SELECT BB.HANDLE FROM Z_CUBOS BB WHERE BB.HANDLE IN(SELECT CC.CUBO FROM Z_CUBOUSUARIOS CC WHERE CC.USUARIO=@USUARIO)))) AND (A.CUBO = @CAMPO(HANDLE))</UserDefinedCriteriaWhereClause>
  <FormUrl>~/aga/a/f/aga_t2477_at3587_hsf5c33bca.aspx</FormUrl>
  <UserDefinedDisableRowSelection>false</UserDefinedDisableRowSelection>
</SimpleGridAttributes>]]></XmlAttributes>
      <Level>Benner</Level>
    </PageWidgetPortable>
  </Widgets>
  <Resources />
</PagePortable>