<?xml version="1.0"?>
<PagePortable xmlns:xsd="http://www.w3.org/2001/XMLSchema" xmlns:xsi="http://www.w3.org/2001/XMLSchema-instance">
  <Title>Informações do documento</Title>
  <Url>~/aga/a/tributos/mdfe/InformacoesDocumento.aspx</Url>
  <AutoGenerated>true</AutoGenerated>
  <EntityPermissionId />
  <TemplateId>MESTRE_DETALHE_ABAS_HORIZONTAIS</TemplateId>
  <Details />
  <Id>AGA_A_TRIBUTOS_MDFE_INFORMACOESDOCUMENTO</Id>
  <Level>Benner</Level>
  <CodeFile />
  <CodeInherits />
  <Widgets>
    <PageWidgetPortable>
      <Id>INFORMAESDODOCUMENTO</Id>
      <Title>Informações do documento</Title>
      <Order>10</Order>
      <ShowTitle>true</ShowTitle>
      <PortletCssClass />
      <FontIcon />
      <Subtitle />
      <ChromeState>Normal</ChromeState>
      <PortletLayout>Default</PortletLayout>
      <WidgetTypeId>AjaxForm</WidgetTypeId>
      <BootstrapCols>12</BootstrapCols>
      <XmlAttributes><![CDATA[<AjaxFormAttributes>
  <CanDelete>true</CanDelete>
  <CanUpdate>true</CanUpdate>
  <CanInsert>true</CanInsert>
  <EntityViewName>TR_MDFEINFORMACAODOCUMENTO.FORM</EntityViewName>
  <FormMode>0</FormMode>
  <IncludeRecordInRecentItems>true</IncludeRecordInRecentItems>
  <UserDefinedCommandsVisible>true</UserDefinedCommandsVisible>
</AjaxFormAttributes>
]]></XmlAttributes>
      <Level>Benner</Level>
    </PageWidgetPortable>
    <PageWidgetPortable>
      <Id>PRODUTOSPERIGOSOS</Id>
      <MasterWidgetId>INFORMAESDODOCUMENTO</MasterWidgetId>
      <Title>Produtos perigosos</Title>
      <Order>20</Order>
      <ShowTitle>true</ShowTitle>
      <PortletCssClass />
      <FontIcon />
      <Subtitle />
      <ChromeState>Normal</ChromeState>
      <PortletLayout>Default</PortletLayout>
      <WidgetTypeId>SimpleGrid</WidgetTypeId>
      <BootstrapCols>12</BootstrapCols>
      <XmlAttributes><![CDATA[<SimpleGridAttributes>
  <CanDelete>true</CanDelete>
  <CanUpdate>true</CanUpdate>
  <CanInsert>true</CanInsert>
  <EntityViewName>TR_MDFEPRODUTOPERIGOSO.GRID</EntityViewName>
  <Mode>0</Mode>
  <UserDefinedSelectColumnVisible>false</UserDefinedSelectColumnVisible>
  <UserDefinedPageSize>10</UserDefinedPageSize>
  <SystemFilterOnly>false</SystemFilterOnly>
  <DisplayRowCommand>true</DisplayRowCommand>
  <CompanyFilterMode>1</CompanyFilterMode>
  <UserDefinedCriteriaWhereClause>(A.INFORMACAODOCUMENTO = @CAMPO(HANDLE))</UserDefinedCriteriaWhereClause>
  <FormUrl>~/aga/a/tributos/mdfe/ProdutosPerigosos.aspx</FormUrl>
  <ShowExport>true</ShowExport>
  <UserDefinedDisableRowSelection>false</UserDefinedDisableRowSelection>
</SimpleGridAttributes>
]]></XmlAttributes>
      <Level>Benner</Level>
    </PageWidgetPortable>
    <PageWidgetPortable>
      <Id>UNIDADESDETRANSPORTE</Id>
      <MasterWidgetId>INFORMAESDODOCUMENTO</MasterWidgetId>
      <Title>Unidades de transporte</Title>
      <Order>30</Order>
      <ShowTitle>true</ShowTitle>
      <PortletCssClass />
      <FontIcon />
      <Subtitle />
      <ChromeState>Normal</ChromeState>
      <PortletLayout>Default</PortletLayout>
      <WidgetTypeId>SimpleGrid</WidgetTypeId>
      <BootstrapCols>12</BootstrapCols>
      <XmlAttributes><![CDATA[<SimpleGridAttributes>
  <CanDelete>true</CanDelete>
  <CanUpdate>true</CanUpdate>
  <CanInsert>true</CanInsert>
  <EntityViewName>TR_MDFEUNIDADETRANSPORTE.GRID</EntityViewName>
  <Mode>0</Mode>
  <UserDefinedSelectColumnVisible>false</UserDefinedSelectColumnVisible>
  <UserDefinedPageSize>10</UserDefinedPageSize>
  <SystemFilterOnly>false</SystemFilterOnly>
  <DisplayRowCommand>true</DisplayRowCommand>
  <CompanyFilterMode>1</CompanyFilterMode>
  <UserDefinedCriteriaWhereClause>(A.INFORMACAODOCUMENTO = @CAMPO(HANDLE))</UserDefinedCriteriaWhereClause>
  <FormUrl>~/aga/a/tributos/mdfe/UnidadesTransporte.aspx</FormUrl>
  <ShowExport>true</ShowExport>
  <UserDefinedDisableRowSelection>false</UserDefinedDisableRowSelection>
</SimpleGridAttributes>
]]></XmlAttributes>
      <Level>Benner</Level>
    </PageWidgetPortable>
  </Widgets>
  <Resources />
</PagePortable>