<?xml version="1.0"?>
<PagePortable xmlns:xsd="http://www.w3.org/2001/XMLSchema" xmlns:xsi="http://www.w3.org/2001/XMLSchema-instance">
  <Title>Cooperativas - Composição da Base Cálculo (M211/M611)</Title>
  <Url>~/aga/a/tributos/Apuracoes/ApuracaoPC/TRPCApuracaoCooperativas/Grid.aspx</Url>
  <AutoGenerated>true</AutoGenerated>
  <EntityPermissionId />
  <TemplateId />
  <Details />
  <Id>AGA_A_TRIBUTOS_APURACOES_APURACAOPC_TRPCAPURACAOCOOPERATIVAS_GRID</Id>
  <Level>Benner</Level>
  <CodeFile />
  <CodeInherits />
  <Widgets>
    <PageWidgetPortable>
      <Id>GRIDTR_PCAPURACAOCOOPERATIVAS</Id>
      <Title>Cooperativas - Composição da Base Cálculo (M211/M611)</Title>
      <Order>100</Order>
      <ShowTitle>true</ShowTitle>
      <PortletCssClass />
      <FontIcon />
      <Subtitle />
      <ChromeState>Normal</ChromeState>
      <PortletLayout>Default</PortletLayout>
      <WidgetTypeId>SimpleGrid</WidgetTypeId>
      <BootstrapCols>12</BootstrapCols>
      <XmlAttributes><![CDATA[<SimpleGridAttributes>
  <CanDelete>true</CanDelete>
  <CanUpdate>true</CanUpdate>
  <CanInsert>true</CanInsert>
  <EntityViewName>TR_PCAPURACAOCOOPERATIVAS.GRID</EntityViewName>
  <Mode>1</Mode>
  <UserDefinedSelectColumnVisible>false</UserDefinedSelectColumnVisible>
  <UserDefinedPageSize>10</UserDefinedPageSize>
  <SystemFilterOnly>false</SystemFilterOnly>
  <DisplayRowCommand>true</DisplayRowCommand>
  <CompanyFilterMode>1</CompanyFilterMode>
  <FormUrl>~/aga/a/tributos/Apuracoes/ApuracaoPC/TRPCApuracaoCooperativas/Form.aspx</FormUrl>
  <ShowExport>true</ShowExport>
  <UserDefinedDisableRowSelection>false</UserDefinedDisableRowSelection>
</SimpleGridAttributes>]]></XmlAttributes>
      <Level>Benner</Level>
    </PageWidgetPortable>
  </Widgets>
  <Resources />
</PagePortable>