<?xml version="1.0"?>
<PagePortable xmlns:xsd="http://www.w3.org/2001/XMLSchema" xmlns:xsi="http://www.w3.org/2001/XMLSchema-instance">
  <Title>Ordem de produção</Title>
  <Url>~/aga/a/OrdemProducao/form.aspx</Url>
  <AutoGenerated>true</AutoGenerated>
  <EntityPermissionId />
  <TemplateId>MESTRE_DETALHE_ABAS_HORIZONTAIS</TemplateId>
  <Details />
  <Id>AGA_A_ORDEMPRODUCAO_FORM</Id>
  <Level>Benner</Level>
  <CodeFile />
  <CodeInherits>Benner.Corporativo.Wes.WebApp.aga.a.OrdemProducao.OrdemProducaoformPage</CodeInherits>
  <Widgets>
    <PageWidgetPortable>
      <Id>ORDEMDEPRODUO</Id>
      <Title>Ordem de produção</Title>
      <Order>10</Order>
      <ShowTitle>true</ShowTitle>
      <PortletCssClass />
      <FontIcon />
      <Subtitle />
      <ChromeState>Normal</ChromeState>
      <PortletLayout>Default</PortletLayout>
      <WidgetTypeId>AjaxForm</WidgetTypeId>
      <BootstrapCols>12</BootstrapCols>
      <XmlAttributes><![CDATA[<AjaxFormAttributes>
  <CanDelete>true</CanDelete>
  <CanUpdate>true</CanUpdate>
  <CanInsert>true</CanInsert>
  <EntityViewName>PR_ORDENSPRODUCAO.CUSTOM.FORM</EntityViewName>
  <FormMode>0</FormMode>
  <IncludeRecordInRecentItems>true</IncludeRecordInRecentItems>
  <UserDefinedCommandsVisible>true</UserDefinedCommandsVisible>
</AjaxFormAttributes>
]]></XmlAttributes>
      <Level>Benner</Level>
    </PageWidgetPortable>
    <PageWidgetPortable>
      <Id>ITENS</Id>
      <MasterWidgetId>ORDEMDEPRODUO</MasterWidgetId>
      <Title>Itens</Title>
      <Order>20</Order>
      <ShowTitle>true</ShowTitle>
      <PortletCssClass />
      <FontIcon />
      <Subtitle />
      <ChromeState>Normal</ChromeState>
      <PortletLayout>Default</PortletLayout>
      <WidgetTypeId>SimpleGrid</WidgetTypeId>
      <BootstrapCols>12</BootstrapCols>
      <XmlAttributes><![CDATA[<SimpleGridAttributes>
  <CanDelete>true</CanDelete>
  <CanUpdate>true</CanUpdate>
  <CanInsert>true</CanInsert>
  <EntityViewName>PR_ORDEMPRODUCAOITENS.CUSTOM.GRID</EntityViewName>
  <Mode>1</Mode>
  <UserDefinedSelectColumnVisible>false</UserDefinedSelectColumnVisible>
  <UserDefinedPageSize>10</UserDefinedPageSize>
  <SystemFilterOnly>false</SystemFilterOnly>
  <DisplayRowCommand>true</DisplayRowCommand>
  <CompanyFilterMode>1</CompanyFilterMode>
  <UserDefinedCriteriaWhereClause>A.ORDEMPRODUCAO = @CAMPO(HANDLE)</UserDefinedCriteriaWhereClause>
  <FormUrl>~/aga/a/OrdemProducaoItem/form.aspx</FormUrl>
  <ShowExport>true</ShowExport>
  <UserDefinedDisableRowSelection>false</UserDefinedDisableRowSelection>
</SimpleGridAttributes>
]]></XmlAttributes>
      <Level>Benner</Level>
    </PageWidgetPortable>
    <PageWidgetPortable>
      <Id>TAREFAS</Id>
      <MasterWidgetId>ORDEMDEPRODUO</MasterWidgetId>
      <Title>Tarefas</Title>
      <Order>25</Order>
      <ShowTitle>true</ShowTitle>
      <PortletCssClass />
      <FontIcon />
      <Subtitle />
      <ChromeState>Normal</ChromeState>
      <PortletLayout>Default</PortletLayout>
      <WidgetTypeId>SimpleGrid</WidgetTypeId>
      <BootstrapCols>12</BootstrapCols>
      <XmlAttributes><![CDATA[<SimpleGridAttributes>
  <CanDelete>true</CanDelete>
  <CanUpdate>true</CanUpdate>
  <CanInsert>true</CanInsert>
  <EntityViewName>PR_ORDEMPRODUCAOTAREFAS.CUSTOM.GRID</EntityViewName>
  <Mode>1</Mode>
  <UserDefinedSelectColumnVisible>false</UserDefinedSelectColumnVisible>
  <UserDefinedPageSize>10</UserDefinedPageSize>
  <SystemFilterOnly>false</SystemFilterOnly>
  <DisplayRowCommand>true</DisplayRowCommand>
  <CompanyFilterMode>1</CompanyFilterMode>
  <UserDefinedCriteriaWhereClause>A.ORDEMPRODUCAO  = @CAMPO(HANDLE)</UserDefinedCriteriaWhereClause>
  <FormUrl>~/aga/a/OrdemProducaoTarefa/form.aspx</FormUrl>
  <ShowExport>true</ShowExport>
  <UserDefinedDisableRowSelection>false</UserDefinedDisableRowSelection>
</SimpleGridAttributes>
]]></XmlAttributes>
      <Level>Benner</Level>
    </PageWidgetPortable>
    <PageWidgetPortable>
      <Id>SERVIOS</Id>
      <MasterWidgetId>ORDEMDEPRODUO</MasterWidgetId>
      <Title>Serviços</Title>
      <Order>30</Order>
      <ShowTitle>true</ShowTitle>
      <PortletCssClass />
      <FontIcon />
      <Subtitle />
      <ChromeState>Normal</ChromeState>
      <PortletLayout>Default</PortletLayout>
      <WidgetTypeId>SimpleGrid</WidgetTypeId>
      <BootstrapCols>12</BootstrapCols>
      <XmlAttributes><![CDATA[<SimpleGridAttributes>
  <CanDelete>true</CanDelete>
  <CanUpdate>true</CanUpdate>
  <CanInsert>true</CanInsert>
  <EntityViewName>PR_ORDEMPRODUCAOSERVICOS.CUSTOM.GRID</EntityViewName>
  <Mode>1</Mode>
  <UserDefinedSelectColumnVisible>false</UserDefinedSelectColumnVisible>
  <UserDefinedPageSize>10</UserDefinedPageSize>
  <SystemFilterOnly>false</SystemFilterOnly>
  <DisplayRowCommand>true</DisplayRowCommand>
  <CompanyFilterMode>1</CompanyFilterMode>
  <UserDefinedCriteriaWhereClause>A.ORDEMPRODUCAO  = @CAMPO(HANDLE)</UserDefinedCriteriaWhereClause>
  <FormUrl>~/aga/a/OrdemProducaoServico/form.aspx</FormUrl>
  <ShowExport>true</ShowExport>
  <UserDefinedDisableRowSelection>false</UserDefinedDisableRowSelection>
</SimpleGridAttributes>
]]></XmlAttributes>
      <Level>Benner</Level>
    </PageWidgetPortable>
    <PageWidgetPortable>
      <Id>INDUSTRIALIZADOS</Id>
      <MasterWidgetId>ORDEMDEPRODUO</MasterWidgetId>
      <Title>Industrializados</Title>
      <Order>40</Order>
      <ShowTitle>true</ShowTitle>
      <PortletCssClass />
      <FontIcon />
      <Subtitle />
      <ChromeState>Normal</ChromeState>
      <PortletLayout>Default</PortletLayout>
      <WidgetTypeId>SimpleGrid</WidgetTypeId>
      <BootstrapCols>12</BootstrapCols>
      <XmlAttributes><![CDATA[<SimpleGridAttributes>
  <CanDelete>true</CanDelete>
  <CanUpdate>true</CanUpdate>
  <CanInsert>true</CanInsert>
  <EntityViewName>PR_ORDEMINDUSTRIALIZADOS.CUSTOM.GRID</EntityViewName>
  <Mode>1</Mode>
  <UserDefinedSelectColumnVisible>false</UserDefinedSelectColumnVisible>
  <UserDefinedPageSize>10</UserDefinedPageSize>
  <SystemFilterOnly>false</SystemFilterOnly>
  <DisplayRowCommand>true</DisplayRowCommand>
  <CompanyFilterMode>1</CompanyFilterMode>
  <UserDefinedCriteriaWhereClause>A.ORDEMPRODUCAO = @CAMPO(HANDLE)</UserDefinedCriteriaWhereClause>
  <FormUrl>~/aga/a/OrdemIndustrializado/form.aspx</FormUrl>
  <ShowExport>true</ShowExport>
  <UserDefinedDisableRowSelection>false</UserDefinedDisableRowSelection>
</SimpleGridAttributes>
]]></XmlAttributes>
      <Level>Benner</Level>
    </PageWidgetPortable>
  </Widgets>
  <Resources />
</PagePortable>