<?xml version="1.0"?>
<PagePortable xmlns:xsd="http://www.w3.org/2001/XMLSchema" xmlns:xsi="http://www.w3.org/2001/XMLSchema-instance">
  <Title>EMPENHOS</Title>
  <Url>~/aga/a/orcamento/empenhoscadastro.aspx</Url>
  <AutoGenerated>true</AutoGenerated>
  <EntityPermissionId />
  <TemplateId>ABAS_HORIZONTAIS</TemplateId>
  <Details />
  <Id>AGA_A_ORCAMENTO_EMPENHOSCADASTRO</Id>
  <Level>Benner</Level>
  <CodeFile />
  <CodeInherits />
  <Widgets>
    <PageWidgetPortable>
      <Id>EMPENHOS</Id>
      <Title>Empenhos</Title>
      <Order>10</Order>
      <ShowTitle>true</ShowTitle>
      <PortletCssClass />
      <FontIcon />
      <Subtitle />
      <ChromeState>Normal</ChromeState>
      <PortletLayout>Default</PortletLayout>
      <WidgetTypeId>AjaxForm</WidgetTypeId>
      <BootstrapCols>12</BootstrapCols>
      <XmlAttributes><![CDATA[<AjaxFormAttributes>
  <CanDelete>false</CanDelete>
  <CanUpdate>false</CanUpdate>
  <CanInsert>false</CanInsert>
  <EntityViewName>CT_EMPENHOS.FORM</EntityViewName>
  <FormMode>0</FormMode>
  <IncludeRecordInRecentItems>true</IncludeRecordInRecentItems>
  <UserDefinedCommandsVisible>true</UserDefinedCommandsVisible>
</AjaxFormAttributes>
]]></XmlAttributes>
      <Level>Benner</Level>
    </PageWidgetPortable>
    <PageWidgetPortable>
      <Id>HISTRICO</Id>
      <MasterWidgetId>EMPENHOS</MasterWidgetId>
      <Title>Histórico</Title>
      <Order>20</Order>
      <ShowTitle>true</ShowTitle>
      <PortletCssClass />
      <FontIcon />
      <Subtitle />
      <ChromeState>Minimized</ChromeState>
      <PortletLayout>Default</PortletLayout>
      <WidgetTypeId>SimpleGrid</WidgetTypeId>
      <BootstrapCols>12</BootstrapCols>
      <XmlAttributes><![CDATA[<SimpleGridAttributes>
  <CanDelete>false</CanDelete>
  <CanUpdate>false</CanUpdate>
  <CanInsert>false</CanInsert>
  <EntityViewName>PD_STATUS.HISTORICO.GRID</EntityViewName>
  <Mode>0</Mode>
  <UserDefinedSelectColumnVisible>false</UserDefinedSelectColumnVisible>
  <UserDefinedPageSize>10</UserDefinedPageSize>
  <SystemFilterOnly>false</SystemFilterOnly>
  <DisplayRowCommand>true</DisplayRowCommand>
  <CompanyFilterMode>1</CompanyFilterMode>
  <UserDefinedCriteriaWhereClause>A.HANDLEREGISTROORIGEM = @CAMPO(HANDLE) AND HANDLETABELAORIGEM = 2150</UserDefinedCriteriaWhereClause>
  <FormUrl>~/aga/a/orcamento/historicomensagem.aspx</FormUrl>
  <ShowExport>true</ShowExport>
  <UserDefinedDisableRowSelection>false</UserDefinedDisableRowSelection>
</SimpleGridAttributes>
]]></XmlAttributes>
      <Level>Benner</Level>
    </PageWidgetPortable>
    <PageWidgetPortable>
      <Id>MOVIMENTAES</Id>
      <MasterWidgetId>EMPENHOS</MasterWidgetId>
      <Title>Movimentações</Title>
      <Order>30</Order>
      <ShowTitle>true</ShowTitle>
      <PortletCssClass />
      <FontIcon />
      <Subtitle />
      <ChromeState>Normal</ChromeState>
      <PortletLayout>Default</PortletLayout>
      <WidgetTypeId>SimpleGrid</WidgetTypeId>
      <BootstrapCols>12</BootstrapCols>
      <XmlAttributes><![CDATA[<SimpleGridAttributes>
  <CanDelete>false</CanDelete>
  <CanUpdate>false</CanUpdate>
  <CanInsert>false</CanInsert>
  <EntityViewName>AGA_ORCAMENTO_CT_EMPENHOMOVIMENTACOES.GRID</EntityViewName>
  <Mode>0</Mode>
  <UserDefinedSelectColumnVisible>false</UserDefinedSelectColumnVisible>
  <UserDefinedPageSize>10</UserDefinedPageSize>
  <SystemFilterOnly>false</SystemFilterOnly>
  <DisplayRowCommand>true</DisplayRowCommand>
  <CompanyFilterMode>1</CompanyFilterMode>
  <UserDefinedCriteriaWhereClause>A.EMPENHO = @CAMPO(HANDLE)</UserDefinedCriteriaWhereClause>
  <FormUrl>~/aga/a/orcamento/movimentacoes.aspx</FormUrl>
  <ShowExport>true</ShowExport>
  <UserDefinedDisableRowSelection>false</UserDefinedDisableRowSelection>
</SimpleGridAttributes>
]]></XmlAttributes>
      <Level>Benner</Level>
    </PageWidgetPortable>
    <PageWidgetPortable>
      <Id>PEDIDOS</Id>
      <MasterWidgetId>EMPENHOS</MasterWidgetId>
      <Title>Pedidos</Title>
      <Order>40</Order>
      <ShowTitle>true</ShowTitle>
      <PortletCssClass />
      <FontIcon />
      <Subtitle />
      <ChromeState>Normal</ChromeState>
      <PortletLayout>Default</PortletLayout>
      <WidgetTypeId>SimpleGrid</WidgetTypeId>
      <BootstrapCols>12</BootstrapCols>
      <XmlAttributes><![CDATA[<SimpleGridAttributes>
  <CanDelete>false</CanDelete>
  <CanUpdate>false</CanUpdate>
  <CanInsert>false</CanInsert>
  <EntityViewName>CT_PEDIDOSEMPENHOS.GRID</EntityViewName>
  <Mode>1</Mode>
  <UserDefinedSelectColumnVisible>false</UserDefinedSelectColumnVisible>
  <UserDefinedPageSize>10</UserDefinedPageSize>
  <SystemFilterOnly>false</SystemFilterOnly>
  <DisplayRowCommand>false</DisplayRowCommand>
  <CompanyFilterMode>1</CompanyFilterMode>
  <UserDefinedCriteriaWhereClause>A.HANDLE IN (SELECT PEDIDO FROM CT_EMPENHOPEDIDO WHERE EMPENHO =@CAMPO(HANDLE)) </UserDefinedCriteriaWhereClause>
  <FormUrl>~/aga/a/orcamento/empenhos/PedidosEmpenhos/Formempenho.aspx</FormUrl>
  <ShowExport>true</ShowExport>
  <UserDefinedDisableRowSelection>false</UserDefinedDisableRowSelection>
</SimpleGridAttributes>
]]></XmlAttributes>
      <Level>Benner</Level>
    </PageWidgetPortable>
  </Widgets>
  <Resources />
</PagePortable>