<?xml version="1.0"?>
<PagePortable xmlns:xsd="http://www.w3.org/2001/XMLSchema" xmlns:xsi="http://www.w3.org/2001/XMLSchema-instance">
  <Title>Filial</Title>
  <Url>~/aga/a/f/aga_t4070_at6288_hs1673fe92.aspx</Url>
  <AutoGenerated>true</AutoGenerated>
  <EntityPermissionId />
  <TemplateId />
  <Details />
  <Id>CARGA_DE_ESTABELECIMENTOS__CARGA_DE_ESTABELECIMENTOS_FILIAIS_FORM</Id>
  <Level>Benner</Level>
  <CodeFile />
  <CodeInherits />
  <Widgets>
    <PageWidgetPortable>
      <Id>FORMULARIO</Id>
      <Title>Filial</Title>
      <Order>1</Order>
      <ShowTitle>true</ShowTitle>
      <PortletCssClass />
      <FontIcon />
      <Subtitle />
      <ChromeState>Normal</ChromeState>
      <PortletLayout>Default</PortletLayout>
      <WidgetTypeId>AjaxForm</WidgetTypeId>
      <BootstrapCols>12</BootstrapCols>
      <XmlAttributes><![CDATA[<AjaxFormAttributes>
  <CanDelete>true</CanDelete>
  <CanUpdate>true</CanUpdate>
  <CanInsert>true</CanInsert>
  <EntityViewName>AGA_TR_ESTABELECIMENTOSFILIAIS.FORM</EntityViewName>
  <FormMode>2</FormMode>
  <IncludeRecordInRecentItems>true</IncludeRecordInRecentItems>
  <UserDefinedCommandsVisible>true</UserDefinedCommandsVisible>
</AjaxFormAttributes>
]]></XmlAttributes>
      <Level>Benner</Level>
    </PageWidgetPortable>
  </Widgets>
  <Resources />
</PagePortable>