<?xml version="1.0"?>
<PagePortable xmlns:xsd="http://www.w3.org/2001/XMLSchema" xmlns:xsi="http://www.w3.org/2001/XMLSchema-instance">
  <Title>Itens</Title>
  <Url>~/aga/a/f/aga_t1836_at2015_hs97779a70.aspx</Url>
  <AutoGenerated>true</AutoGenerated>
  <EntityPermissionId />
  <TemplateId />
  <Details />
  <Id>CARGA_DE_ITENS_OP_SOLEITURA__ITENS_FORM</Id>
  <Level>Benner</Level>
  <CodeFile />
  <CodeInherits />
  <Widgets>
    <PageWidgetPortable>
      <Id>FORMULARIO</Id>
      <Title>Itens</Title>
      <Order>1</Order>
      <ShowTitle>true</ShowTitle>
      <PortletCssClass />
      <FontIcon />
      <Subtitle />
      <ChromeState>Normal</ChromeState>
      <PortletLayout>Default</PortletLayout>
      <WidgetTypeId>AjaxForm</WidgetTypeId>
      <BootstrapCols>12</BootstrapCols>
      <XmlAttributes><![CDATA[<AjaxFormAttributes>
  <EntityViewName>AGA_PR_ORDEMPRODUCAOITENS.FORM</EntityViewName>
  <CanDelete>false</CanDelete>
  <CanUpdate>false</CanUpdate>
  <CanInsert>false</CanInsert>
  <IncludeRecordInRecentItems>true</IncludeRecordInRecentItems>
  <UserDefinedCriteriaWhereClause>'forcar_carga_form'='forcar_carga_form'</UserDefinedCriteriaWhereClause>
  <UserDefinedCommandsVisible>true</UserDefinedCommandsVisible>
</AjaxFormAttributes>]]></XmlAttributes>
      <Level>Benner</Level>
    </PageWidgetPortable>
    <PageWidgetPortable>
      <Id>WIDGET_6593</Id>
      <MasterWidgetId>FORMULARIO</MasterWidgetId>
      <Title>Consumo previsto</Title>
      <Order>10</Order>
      <ShowTitle>false</ShowTitle>
      <PortletCssClass />
      <FontIcon />
      <Subtitle />
      <ChromeState>Normal</ChromeState>
      <PortletLayout>Default</PortletLayout>
      <WidgetTypeId>SimpleGrid</WidgetTypeId>
      <BootstrapCols>12</BootstrapCols>
      <XmlAttributes><![CDATA[<SimpleGridAttributes>
  <EntityViewName>AGA_PR_ITEMCONSUMOS.GRID</EntityViewName>
  <CanDelete>false</CanDelete>
  <CanUpdate>false</CanUpdate>
  <CanInsert>false</CanInsert>
  <Mode>1</Mode>
  <UserDefinedSelectColumnVisible>false</UserDefinedSelectColumnVisible>
  <UserDefinedPageSize>10</UserDefinedPageSize>
  <SystemFilterOnly>false</SystemFilterOnly>
  <DisplayRowCommand>true</DisplayRowCommand>
  <CompanyFilterMode>2</CompanyFilterMode>
  <UserDefinedCriteriaWhereClause>(A.APONTAMENTO IN (SELECT B.HANDLE FROM PR_ORDEMPRODUCAOAPONTAMENTOS B WHERE (B.STATUS=1) OR (B.STATUS=3))) AND (A.ORDEMPRODUCAOITEM = @CAMPO(HANDLE))</UserDefinedCriteriaWhereClause>
  <FormUrl>~/aga/a/f/aga_t1843_at6593_hsa3474836.aspx</FormUrl>
  <UserDefinedDisableRowSelection>false</UserDefinedDisableRowSelection>
</SimpleGridAttributes>]]></XmlAttributes>
      <Level>Benner</Level>
    </PageWidgetPortable>
    <PageWidgetPortable>
      <Id>WIDGET_6594</Id>
      <MasterWidgetId>FORMULARIO</MasterWidgetId>
      <Title>Consumo realizado</Title>
      <Order>15</Order>
      <ShowTitle>false</ShowTitle>
      <PortletCssClass />
      <FontIcon />
      <Subtitle />
      <ChromeState>Normal</ChromeState>
      <PortletLayout>Default</PortletLayout>
      <WidgetTypeId>SimpleGrid</WidgetTypeId>
      <BootstrapCols>12</BootstrapCols>
      <XmlAttributes><![CDATA[<SimpleGridAttributes>
  <EntityViewName>AGA_PR_ITEMCONSUMOS.GRID</EntityViewName>
  <CanDelete>false</CanDelete>
  <CanUpdate>false</CanUpdate>
  <CanInsert>false</CanInsert>
  <Mode>1</Mode>
  <UserDefinedSelectColumnVisible>false</UserDefinedSelectColumnVisible>
  <UserDefinedPageSize>10</UserDefinedPageSize>
  <SystemFilterOnly>false</SystemFilterOnly>
  <DisplayRowCommand>true</DisplayRowCommand>
  <CompanyFilterMode>2</CompanyFilterMode>
  <UserDefinedCriteriaWhereClause>(A.APONTAMENTO IN (SELECT B.HANDLE FROM PR_ORDEMPRODUCAOAPONTAMENTOS B WHERE (B.STATUS=2))) AND (A.ORDEMPRODUCAOITEM = @CAMPO(HANDLE))</UserDefinedCriteriaWhereClause>
  <FormUrl>~/aga/a/f/aga_t1843_at6594_hsfbab6797.aspx</FormUrl>
  <UserDefinedDisableRowSelection>false</UserDefinedDisableRowSelection>
</SimpleGridAttributes>]]></XmlAttributes>
      <Level>Benner</Level>
    </PageWidgetPortable>
    <PageWidgetPortable>
      <Id>WIDGET_6595</Id>
      <MasterWidgetId>FORMULARIO</MasterWidgetId>
      <Title>Lotes</Title>
      <Order>20</Order>
      <ShowTitle>false</ShowTitle>
      <PortletCssClass />
      <FontIcon />
      <Subtitle />
      <ChromeState>Normal</ChromeState>
      <PortletLayout>Default</PortletLayout>
      <WidgetTypeId>SimpleGrid</WidgetTypeId>
      <BootstrapCols>12</BootstrapCols>
      <XmlAttributes><![CDATA[<SimpleGridAttributes>
  <EntityViewName>AGA_PR_ORDEMPRODUCAOITEMLOTES.GRID</EntityViewName>
  <CanDelete>false</CanDelete>
  <CanUpdate>false</CanUpdate>
  <CanInsert>false</CanInsert>
  <Mode>1</Mode>
  <UserDefinedSelectColumnVisible>false</UserDefinedSelectColumnVisible>
  <UserDefinedPageSize>10</UserDefinedPageSize>
  <SystemFilterOnly>false</SystemFilterOnly>
  <DisplayRowCommand>true</DisplayRowCommand>
  <CompanyFilterMode>2</CompanyFilterMode>
  <UserDefinedCriteriaWhereClause>(A.ORDEMPRODUCAOITEM = @CAMPO(HANDLE))</UserDefinedCriteriaWhereClause>
  <FormUrl>~/aga/a/f/aga_t1974_at6595_hs4f0b66e0.aspx</FormUrl>
  <UserDefinedDisableRowSelection>false</UserDefinedDisableRowSelection>
</SimpleGridAttributes>]]></XmlAttributes>
      <Level>Benner</Level>
    </PageWidgetPortable>
    <PageWidgetPortable>
      <Id>WIDGET_6598</Id>
      <MasterWidgetId>FORMULARIO</MasterWidgetId>
      <Title>Ordem de compra</Title>
      <Order>25</Order>
      <ShowTitle>false</ShowTitle>
      <PortletCssClass />
      <FontIcon />
      <Subtitle />
      <ChromeState>Normal</ChromeState>
      <PortletLayout>Default</PortletLayout>
      <WidgetTypeId>SimpleGrid</WidgetTypeId>
      <BootstrapCols>12</BootstrapCols>
      <XmlAttributes><![CDATA[<SimpleGridAttributes>
  <EntityViewName>AGA_CP_ORDENSCOMPRA.GRID</EntityViewName>
  <CanDelete>false</CanDelete>
  <CanUpdate>false</CanUpdate>
  <CanInsert>false</CanInsert>
  <Mode>1</Mode>
  <UserDefinedSelectColumnVisible>false</UserDefinedSelectColumnVisible>
  <UserDefinedPageSize>10</UserDefinedPageSize>
  <SystemFilterOnly>false</SystemFilterOnly>
  <DisplayRowCommand>true</DisplayRowCommand>
  <CompanyFilterMode>2</CompanyFilterMode>
  <UserDefinedCriteriaWhereClause>A.HANDLE IN ( SELECT O.ORDEMCOMPRA  FROM CP_ORDENSCOMPRAITENS O WHERE O.HANDLE IN (SELECT I.ORDEMCOMPRAITEM FROM PR_ORDEMPRODUCAOITENS I WHERE I.HANDLE = @RASTRO(PR_ORDEMPRODUCAOITENS) ) )</UserDefinedCriteriaWhereClause>
  <FormUrl>~/aga/a/f/aga_t1529_at6598_hs80826de1.aspx</FormUrl>
  <UserDefinedDisableRowSelection>false</UserDefinedDisableRowSelection>
</SimpleGridAttributes>]]></XmlAttributes>
      <Level>Benner</Level>
    </PageWidgetPortable>
    <PageWidgetPortable>
      <Id>WIDGET_6596</Id>
      <MasterWidgetId>FORMULARIO</MasterWidgetId>
      <Title>Requisição consumo de produção</Title>
      <Order>30</Order>
      <ShowTitle>false</ShowTitle>
      <PortletCssClass />
      <FontIcon />
      <Subtitle />
      <ChromeState>Normal</ChromeState>
      <PortletLayout>Default</PortletLayout>
      <WidgetTypeId>SimpleGrid</WidgetTypeId>
      <BootstrapCols>12</BootstrapCols>
      <XmlAttributes><![CDATA[<SimpleGridAttributes>
  <EntityViewName>AGA_CP_REQUISICOESPAI.GRID</EntityViewName>
  <CanDelete>false</CanDelete>
  <CanUpdate>false</CanUpdate>
  <CanInsert>false</CanInsert>
  <Mode>1</Mode>
  <UserDefinedSelectColumnVisible>false</UserDefinedSelectColumnVisible>
  <UserDefinedPageSize>10</UserDefinedPageSize>
  <SystemFilterOnly>false</SystemFilterOnly>
  <DisplayRowCommand>true</DisplayRowCommand>
  <CompanyFilterMode>2</CompanyFilterMode>
  <UserDefinedCriteriaWhereClause>A.HANDLE IN (SELECT REQUISICAOPAI FROM CP_REQUISICOES WHERE HANDLE IN (SELECT REQUISICAO FROM PR_REQUISICOESCONSUMOITEM WHERE ORDEMPRODUCAOITEM =  @RASTRO(PR_ORDEMPRODUCAOITENS)))</UserDefinedCriteriaWhereClause>
  <FormUrl>~/aga/a/f/aga_t2311_at6596_hs2e5ce26.aspx</FormUrl>
  <UserDefinedDisableRowSelection>false</UserDefinedDisableRowSelection>
</SimpleGridAttributes>]]></XmlAttributes>
      <Level>Benner</Level>
    </PageWidgetPortable>
    <PageWidgetPortable>
      <Id>WIDGET_6597</Id>
      <MasterWidgetId>FORMULARIO</MasterWidgetId>
      <Title>Requisições de compra</Title>
      <Order>35</Order>
      <ShowTitle>false</ShowTitle>
      <PortletCssClass />
      <FontIcon />
      <Subtitle />
      <ChromeState>Normal</ChromeState>
      <PortletLayout>Default</PortletLayout>
      <WidgetTypeId>SimpleGrid</WidgetTypeId>
      <BootstrapCols>12</BootstrapCols>
      <XmlAttributes><![CDATA[<SimpleGridAttributes>
  <EntityViewName>AGA_CP_REQUISICOESPAI.GRID</EntityViewName>
  <CanDelete>false</CanDelete>
  <CanUpdate>false</CanUpdate>
  <CanInsert>false</CanInsert>
  <Mode>1</Mode>
  <UserDefinedSelectColumnVisible>false</UserDefinedSelectColumnVisible>
  <UserDefinedPageSize>10</UserDefinedPageSize>
  <SystemFilterOnly>false</SystemFilterOnly>
  <DisplayRowCommand>true</DisplayRowCommand>
  <CompanyFilterMode>2</CompanyFilterMode>
  <UserDefinedCriteriaWhereClause>A.HANDLE IN ( SELECT REQUISICAOPAI FROM CP_REQUISICOES
  WHERE HANDLE = (SELECT REQUISICAO FROM PR_ORDEMPRODUCAOITENS WHERE HANDLE = @RASTRO(PR_ORDEMPRODUCAOITENS)))</UserDefinedCriteriaWhereClause>
  <FormUrl>~/aga/a/f/aga_t2311_at6597_hs35bec45b.aspx</FormUrl>
  <UserDefinedDisableRowSelection>false</UserDefinedDisableRowSelection>
</SimpleGridAttributes>]]></XmlAttributes>
      <Level>Benner</Level>
    </PageWidgetPortable>
    <PageWidgetPortable>
      <Id>WIDGET_7981</Id>
      <MasterWidgetId>FORMULARIO</MasterWidgetId>
      <Title>Substitutos</Title>
      <Order>40</Order>
      <ShowTitle>false</ShowTitle>
      <PortletCssClass />
      <FontIcon />
      <Subtitle />
      <ChromeState>Normal</ChromeState>
      <PortletLayout>Default</PortletLayout>
      <WidgetTypeId>SimpleGrid</WidgetTypeId>
      <BootstrapCols>12</BootstrapCols>
      <XmlAttributes><![CDATA[<SimpleGridAttributes>
  <EntityViewName>AGA_PR_ORDEMPRODUCAOITENSSUBST.GRID</EntityViewName>
  <CanDelete>false</CanDelete>
  <CanUpdate>false</CanUpdate>
  <CanInsert>false</CanInsert>
  <Mode>1</Mode>
  <UserDefinedSelectColumnVisible>false</UserDefinedSelectColumnVisible>
  <UserDefinedPageSize>10</UserDefinedPageSize>
  <SystemFilterOnly>false</SystemFilterOnly>
  <DisplayRowCommand>true</DisplayRowCommand>
  <CompanyFilterMode>2</CompanyFilterMode>
  <UserDefinedCriteriaWhereClause>(A.ORDEMPRODUCAOITENS = @CAMPO(HANDLE))</UserDefinedCriteriaWhereClause>
  <FormUrl>~/aga/a/f/aga_t2534_at7981_hs25fea8a1.aspx</FormUrl>
  <UserDefinedDisableRowSelection>false</UserDefinedDisableRowSelection>
</SimpleGridAttributes>]]></XmlAttributes>
      <Level>Benner</Level>
    </PageWidgetPortable>
  </Widgets>
  <Resources />
</PagePortable>