<?xml version="1.0"?>
<PagePortable xmlns:xsd="http://www.w3.org/2001/XMLSchema" xmlns:xsi="http://www.w3.org/2001/XMLSchema-instance">
  <Title>Negócios</Title>
  <Url>~/aga/a/f/aga_t2200_at2778_hs2d0ec547.aspx</Url>
  <AutoGenerated>true</AutoGenerated>
  <EntityPermissionId />
  <TemplateId />
  <Details />
  <Id>EVENTOS__EXPOSICOES_FORM</Id>
  <Level>Benner</Level>
  <CodeFile />
  <CodeInherits />
  <Widgets>
    <PageWidgetPortable>
      <Id>FORMULARIO</Id>
      <Title>Negócios</Title>
      <Order>1</Order>
      <ShowTitle>true</ShowTitle>
      <PortletCssClass />
      <FontIcon />
      <Subtitle />
      <ChromeState>Normal</ChromeState>
      <PortletLayout>Default</PortletLayout>
      <WidgetTypeId>AjaxForm</WidgetTypeId>
      <BootstrapCols>12</BootstrapCols>
      <XmlAttributes><![CDATA[<AjaxFormAttributes>
  <EntityViewName>AGA_EV_EXPOSICOES.FORM</EntityViewName>
  <CanDelete>true</CanDelete>
  <CanUpdate>true</CanUpdate>
  <CanInsert>true</CanInsert>
  <IncludeRecordInRecentItems>true</IncludeRecordInRecentItems>
  <UserDefinedCriteriaWhereClause>'forcar_carga_form'='forcar_carga_form'</UserDefinedCriteriaWhereClause>
  <UserDefinedCommandsVisible>true</UserDefinedCommandsVisible>
</AjaxFormAttributes>]]></XmlAttributes>
      <Level>Benner</Level>
    </PageWidgetPortable>
    <PageWidgetPortable>
      <Id>WIDGET_2782</Id>
      <MasterWidgetId>FORMULARIO</MasterWidgetId>
      <Title>Coordenação</Title>
      <Order>10</Order>
      <ShowTitle>false</ShowTitle>
      <PortletCssClass />
      <FontIcon />
      <Subtitle />
      <ChromeState>Normal</ChromeState>
      <PortletLayout>Default</PortletLayout>
      <WidgetTypeId>SimpleGrid</WidgetTypeId>
      <BootstrapCols>12</BootstrapCols>
      <XmlAttributes><![CDATA[<SimpleGridAttributes>
  <EntityViewName>AGA_EV_EXPOSICAOCOORDENADORES.GRID</EntityViewName>
  <CanDelete>true</CanDelete>
  <CanUpdate>true</CanUpdate>
  <CanInsert>true</CanInsert>
  <Mode>1</Mode>
  <UserDefinedSelectColumnVisible>false</UserDefinedSelectColumnVisible>
  <UserDefinedPageSize>10</UserDefinedPageSize>
  <SystemFilterOnly>false</SystemFilterOnly>
  <DisplayRowCommand>true</DisplayRowCommand>
  <CompanyFilterMode>2</CompanyFilterMode>
  <UserDefinedCriteriaWhereClause>(A.EXPOSICAO = @CAMPO(HANDLE))</UserDefinedCriteriaWhereClause>
  <FormUrl>~/aga/a/f/aga_t2204_at2782_hs616bde73.aspx</FormUrl>
  <UserDefinedDisableRowSelection>false</UserDefinedDisableRowSelection>
</SimpleGridAttributes>]]></XmlAttributes>
      <Level>Benner</Level>
    </PageWidgetPortable>
    <PageWidgetPortable>
      <Id>WIDGET_2781</Id>
      <MasterWidgetId>FORMULARIO</MasterWidgetId>
      <Title>Fornecedores</Title>
      <Order>15</Order>
      <ShowTitle>false</ShowTitle>
      <PortletCssClass />
      <FontIcon />
      <Subtitle />
      <ChromeState>Normal</ChromeState>
      <PortletLayout>Default</PortletLayout>
      <WidgetTypeId>SimpleGrid</WidgetTypeId>
      <BootstrapCols>12</BootstrapCols>
      <XmlAttributes><![CDATA[<SimpleGridAttributes>
  <EntityViewName>AGA_EV_EXPOSICAOFORNECEDORES.GRID</EntityViewName>
  <CanDelete>true</CanDelete>
  <CanUpdate>true</CanUpdate>
  <CanInsert>true</CanInsert>
  <Mode>1</Mode>
  <UserDefinedSelectColumnVisible>false</UserDefinedSelectColumnVisible>
  <UserDefinedPageSize>10</UserDefinedPageSize>
  <SystemFilterOnly>false</SystemFilterOnly>
  <DisplayRowCommand>true</DisplayRowCommand>
  <CompanyFilterMode>2</CompanyFilterMode>
  <UserDefinedCriteriaWhereClause>(A.EXPOSICAO = @CAMPO(HANDLE))</UserDefinedCriteriaWhereClause>
  <FormUrl>~/aga/a/f/aga_t2203_at2781_hs6b2ea405.aspx</FormUrl>
  <UserDefinedDisableRowSelection>false</UserDefinedDisableRowSelection>
</SimpleGridAttributes>]]></XmlAttributes>
      <Level>Benner</Level>
    </PageWidgetPortable>
    <PageWidgetPortable>
      <Id>WIDGET_2779</Id>
      <MasterWidgetId>FORMULARIO</MasterWidgetId>
      <Title>Locais</Title>
      <Order>20</Order>
      <ShowTitle>false</ShowTitle>
      <PortletCssClass />
      <FontIcon />
      <Subtitle />
      <ChromeState>Normal</ChromeState>
      <PortletLayout>Default</PortletLayout>
      <WidgetTypeId>SimpleGrid</WidgetTypeId>
      <BootstrapCols>12</BootstrapCols>
      <XmlAttributes><![CDATA[<SimpleGridAttributes>
  <EntityViewName>AGA_EV_EXPOSICAOLOCAIS.GRID</EntityViewName>
  <CanDelete>true</CanDelete>
  <CanUpdate>true</CanUpdate>
  <CanInsert>true</CanInsert>
  <Mode>1</Mode>
  <UserDefinedSelectColumnVisible>false</UserDefinedSelectColumnVisible>
  <UserDefinedPageSize>10</UserDefinedPageSize>
  <SystemFilterOnly>false</SystemFilterOnly>
  <DisplayRowCommand>true</DisplayRowCommand>
  <CompanyFilterMode>2</CompanyFilterMode>
  <UserDefinedCriteriaWhereClause>(A.EXPOSICAO = @CAMPO(HANDLE))</UserDefinedCriteriaWhereClause>
  <FormUrl>~/aga/a/f/aga_t2201_at2779_hsa48ed45f.aspx</FormUrl>
  <UserDefinedDisableRowSelection>false</UserDefinedDisableRowSelection>
</SimpleGridAttributes>]]></XmlAttributes>
      <Level>Benner</Level>
    </PageWidgetPortable>
    <PageWidgetPortable>
      <Id>WIDGET_2780</Id>
      <MasterWidgetId>FORMULARIO</MasterWidgetId>
      <Title>Patrocinadores</Title>
      <Order>25</Order>
      <ShowTitle>false</ShowTitle>
      <PortletCssClass />
      <FontIcon />
      <Subtitle />
      <ChromeState>Normal</ChromeState>
      <PortletLayout>Default</PortletLayout>
      <WidgetTypeId>SimpleGrid</WidgetTypeId>
      <BootstrapCols>12</BootstrapCols>
      <XmlAttributes><![CDATA[<SimpleGridAttributes>
  <EntityViewName>AGA_EV_EXPOSICAOPATROCINADORES.GRID</EntityViewName>
  <CanDelete>true</CanDelete>
  <CanUpdate>true</CanUpdate>
  <CanInsert>true</CanInsert>
  <Mode>1</Mode>
  <UserDefinedSelectColumnVisible>false</UserDefinedSelectColumnVisible>
  <UserDefinedPageSize>10</UserDefinedPageSize>
  <SystemFilterOnly>false</SystemFilterOnly>
  <DisplayRowCommand>true</DisplayRowCommand>
  <CompanyFilterMode>2</CompanyFilterMode>
  <UserDefinedCriteriaWhereClause>(A.EXPOSICAO = @CAMPO(HANDLE))</UserDefinedCriteriaWhereClause>
  <FormUrl>~/aga/a/f/aga_t2202_at2780_hs2b8f4b72.aspx</FormUrl>
  <UserDefinedDisableRowSelection>false</UserDefinedDisableRowSelection>
</SimpleGridAttributes>]]></XmlAttributes>
      <Level>Benner</Level>
    </PageWidgetPortable>
  </Widgets>
  <Resources />
</PagePortable>