<?xml version="1.0"?>
<PagePortable xmlns:xsd="http://www.w3.org/2001/XMLSchema" xmlns:xsi="http://www.w3.org/2001/XMLSchema-instance">
  <Title>Fornecedores</Title>
  <Url>~/aga/a/g/aga_t717_at946_hs7ca6d58.aspx</Url>
  <AutoGenerated>true</AutoGenerated>
  <EntityPermissionId />
  <TemplateId />
  <Details />
  <Id>FINANCEIRO__FORNECEDORES_GRID</Id>
  <Level>Benner</Level>
  <CodeFile />
  <CodeInherits />
  <Widgets>
    <PageWidgetPortable>
      <Id>GRID</Id>
      <Title>Fornecedores</Title>
      <Order>1</Order>
      <ShowTitle>true</ShowTitle>
      <PortletCssClass />
      <FontIcon />
      <Subtitle />
      <ChromeState>Normal</ChromeState>
      <PortletLayout>Default</PortletLayout>
      <WidgetTypeId>SimpleGrid</WidgetTypeId>
      <BootstrapCols>12</BootstrapCols>
      <XmlAttributes><![CDATA[<SimpleGridAttributes>
  <CanDelete>true</CanDelete>
  <CanUpdate>true</CanUpdate>
  <CanInsert>true</CanInsert>
  <EntityViewName>GN_PESSOAS.CUSTOM.FORNECEDOR.GRID</EntityViewName>
  <Mode>1</Mode>
  <UserDefinedSelectColumnVisible>false</UserDefinedSelectColumnVisible>
  <UserDefinedPageSize>10</UserDefinedPageSize>
  <SystemFilterOnly>false</SystemFilterOnly>
  <DisplayRowCommand>true</DisplayRowCommand>
  <CompanyFilterMode>2</CompanyFilterMode>
  <UserDefinedCriteriaWhereClause>(A.EHFORNECEDOR='S' AND A.FORNECEDORCONTRATANTE is NULL AND A.EHTERCEIRO='N')</UserDefinedCriteriaWhereClause>
  <FormUrl>~/aga/a/genericos/pessoasfornecedores.aspx</FormUrl>
  <ShowExport>true</ShowExport>
  <UserDefinedDisableRowSelection>false</UserDefinedDisableRowSelection>
</SimpleGridAttributes>
]]></XmlAttributes>
      <Level>Benner</Level>
    </PageWidgetPortable>
  </Widgets>
  <Resources>
    <PageResourcePortable>
      <Id>0936C8C59C1C436582306EC56D07FF2F</Id>
      <ResourceType>CSS</ResourceType>
      <Content><![CDATA[#GRID th, td {
    white-space:nowrap !important;
}]]></Content>
      <Level>Benner</Level>
    </PageResourcePortable>
  </Resources>
</PagePortable>