<?xml version="1.0"?>
<PagePortable xmlns:xsd="http://www.w3.org/2001/XMLSchema" xmlns:xsi="http://www.w3.org/2001/XMLSchema-instance">
  <Title>Log do período</Title>
  <Url>~/aga/a/Contabil/SEICED/SeiPeriodolog9477Form.aspx</Url>
  <AutoGenerated>true</AutoGenerated>
  <EntityPermissionId />
  <TemplateId />
  <Details />
  <Id>SEI_PERIODOLOG_9477_FORM</Id>
  <Level>Benner</Level>
  <CodeFile />
  <CodeInherits />
  <Widgets>
    <PageWidgetPortable>
      <Id>SEI_PERIODOLOG_9477_FORM</Id>
      <Title>Log do período</Title>
      <Order>10</Order>
      <ShowTitle>true</ShowTitle>
      <PortletCssClass />
      <FontIcon />
      <Subtitle />
      <ChromeState>Normal</ChromeState>
      <PortletLayout>Default</PortletLayout>
      <WidgetTypeId>AjaxForm</WidgetTypeId>
      <BootstrapCols>12</BootstrapCols>
      <XmlAttributes><![CDATA[<AjaxFormAttributes>
                      <CanDelete>false</CanDelete>
                      <CanUpdate>false</CanUpdate>
                      <CanInsert>false</CanInsert>
                      <EntityViewName>SEI_PERIODOLOG_LOG.CUSTOM.FORM</EntityViewName>
                      <FormMode>0</FormMode>
                      <IncludeRecordInRecentItems>true</IncludeRecordInRecentItems>
                      <UserDefinedCommandsVisible>true</UserDefinedCommandsVisible>
                    </AjaxFormAttributes>]]></XmlAttributes>
      <Level>Benner</Level>
    </PageWidgetPortable>
  </Widgets>
  <Resources />
</PagePortable>