<?xml version="1.0"?>
<PagePortable xmlns:xsd="http://www.w3.org/2001/XMLSchema" xmlns:xsi="http://www.w3.org/2001/XMLSchema-instance">
  <Title>Retificações</Title>
  <Url>~/aga/a/f/aga_t4623_at6884_hs7a19b190.aspx</Url>
  <AutoGenerated>true</AutoGenerated>
  <EntityPermissionId />
  <TemplateId />
  <Details />
  <Id>SISCOSERV_RVS__TR_SS_RVS_RETIFICACOES_FORM</Id>
  <Level>Benner</Level>
  <CodeFile />
  <CodeInherits />
  <Widgets>
    <PageWidgetPortable>
      <Id>FORMULARIO</Id>
      <Title>Retificações</Title>
      <Order>1</Order>
      <ShowTitle>true</ShowTitle>
      <PortletCssClass />
      <FontIcon />
      <Subtitle />
      <ChromeState>Normal</ChromeState>
      <PortletLayout>Default</PortletLayout>
      <WidgetTypeId>AjaxForm</WidgetTypeId>
      <BootstrapCols>12</BootstrapCols>
      <XmlAttributes><![CDATA[<AjaxFormAttributes>
  <EntityViewName>AGA_TR_SSRVSRETIFICACOES.FORM</EntityViewName>
  <CanDelete>true</CanDelete>
  <CanUpdate>true</CanUpdate>
  <CanInsert>true</CanInsert>
  <IncludeRecordInRecentItems>true</IncludeRecordInRecentItems>
  <UserDefinedCriteriaWhereClause>'forcar_carga_form'='forcar_carga_form'</UserDefinedCriteriaWhereClause>
  <UserDefinedCommandsVisible>true</UserDefinedCommandsVisible>
</AjaxFormAttributes>]]></XmlAttributes>
      <Level>Benner</Level>
    </PageWidgetPortable>
    <PageWidgetPortable>
      <Id>WIDGET_6882</Id>
      <MasterWidgetId>FORMULARIO</MasterWidgetId>
      <Title>Exportação de Bens</Title>
      <Order>10</Order>
      <ShowTitle>false</ShowTitle>
      <PortletCssClass />
      <FontIcon />
      <Subtitle />
      <ChromeState>Normal</ChromeState>
      <PortletLayout>Default</PortletLayout>
      <WidgetTypeId>SimpleGrid</WidgetTypeId>
      <BootstrapCols>12</BootstrapCols>
      <XmlAttributes><![CDATA[<SimpleGridAttributes>
  <EntityViewName>AGA_TR_SSRVSBENSEXPORTACAO.GRID</EntityViewName>
  <CanDelete>true</CanDelete>
  <CanUpdate>true</CanUpdate>
  <CanInsert>true</CanInsert>
  <Mode>1</Mode>
  <UserDefinedSelectColumnVisible>false</UserDefinedSelectColumnVisible>
  <UserDefinedPageSize>10</UserDefinedPageSize>
  <SystemFilterOnly>false</SystemFilterOnly>
  <DisplayRowCommand>true</DisplayRowCommand>
  <CompanyFilterMode>2</CompanyFilterMode>
  <UserDefinedCriteriaWhereClause>(A.RETIFICACAORVS = @CAMPO(HANDLE))</UserDefinedCriteriaWhereClause>
  <FormUrl>~/aga/a/f/aga_t4624_at6882_hs50e8e118.aspx</FormUrl>
  <UserDefinedDisableRowSelection>false</UserDefinedDisableRowSelection>
</SimpleGridAttributes>]]></XmlAttributes>
      <Level>Benner</Level>
    </PageWidgetPortable>
    <PageWidgetPortable>
      <Id>WIDGET_6883</Id>
      <MasterWidgetId>FORMULARIO</MasterWidgetId>
      <Title>Operações</Title>
      <Order>15</Order>
      <ShowTitle>false</ShowTitle>
      <PortletCssClass />
      <FontIcon />
      <Subtitle />
      <ChromeState>Normal</ChromeState>
      <PortletLayout>Default</PortletLayout>
      <WidgetTypeId>SimpleGrid</WidgetTypeId>
      <BootstrapCols>12</BootstrapCols>
      <XmlAttributes><![CDATA[<SimpleGridAttributes>
  <EntityViewName>AGA_TR_SSRVSRETIFICACAOOPERACAO.GRID</EntityViewName>
  <CanDelete>true</CanDelete>
  <CanUpdate>true</CanUpdate>
  <CanInsert>true</CanInsert>
  <Mode>1</Mode>
  <UserDefinedSelectColumnVisible>false</UserDefinedSelectColumnVisible>
  <UserDefinedPageSize>10</UserDefinedPageSize>
  <SystemFilterOnly>false</SystemFilterOnly>
  <DisplayRowCommand>true</DisplayRowCommand>
  <CompanyFilterMode>2</CompanyFilterMode>
  <UserDefinedCriteriaWhereClause>(A.RETIFICACAORVS = @CAMPO(HANDLE))</UserDefinedCriteriaWhereClause>
  <FormUrl>~/aga/a/f/aga_t5825_at6883_hse0e6f2b9.aspx</FormUrl>
  <UserDefinedDisableRowSelection>false</UserDefinedDisableRowSelection>
</SimpleGridAttributes>]]></XmlAttributes>
      <Level>Benner</Level>
    </PageWidgetPortable>
  </Widgets>
  <Resources />
</PagePortable>