<?xml version="1.0"?>
<PagePortable xmlns:xsd="http://www.w3.org/2001/XMLSchema" xmlns:xsi="http://www.w3.org/2001/XMLSchema-instance">
  <Title>Aviso para eventos de NF-e</Title>
  <Url>~/aga/a/f/aga_t4089_at7623_hs4e60d873.aspx</Url>
  <AutoGenerated>true</AutoGenerated>
  <EntityPermissionId />
  <TemplateId />
  <Details />
  <Id>SUBCARGAS_DOCUMENTOSELETRONICOS__AVISOEVENTOSNFE_FORM</Id>
  <Level>Benner</Level>
  <CodeFile />
  <CodeInherits />
  <Widgets>
    <PageWidgetPortable>
      <Id>FORMULARIO</Id>
      <Title>Aviso para eventos de NF-e</Title>
      <Order>1</Order>
      <ShowTitle>true</ShowTitle>
      <PortletCssClass />
      <FontIcon />
      <Subtitle />
      <ChromeState>Normal</ChromeState>
      <PortletLayout>Default</PortletLayout>
      <WidgetTypeId>AjaxForm</WidgetTypeId>
      <BootstrapCols>12</BootstrapCols>
      <XmlAttributes><![CDATA[<AjaxFormAttributes>
  <EntityViewName>AGA_TR_NFEAVISOEVENTOS.FORM</EntityViewName>
  <CanDelete>true</CanDelete>
  <CanUpdate>true</CanUpdate>
  <CanInsert>true</CanInsert>
  <IncludeRecordInRecentItems>true</IncludeRecordInRecentItems>
  <UserDefinedCriteriaWhereClause>'forcar_carga_form'='forcar_carga_form'</UserDefinedCriteriaWhereClause>
  <UserDefinedCommandsVisible>true</UserDefinedCommandsVisible>
</AjaxFormAttributes>]]></XmlAttributes>
      <Level>Benner</Level>
    </PageWidgetPortable>
  </Widgets>
  <Resources />
</PagePortable>