<?xml version="1.0"?>
<ScriptPortable xmlns:xsd="http://www.w3.org/2001/XMLSchema" xmlns:xsi="http://www.w3.org/2001/XMLSchema-instance">
  <ViewName>CN_APONTAMENTOS.CONTRATOS.GRID</ViewName>
  <EntityName>CN_APONTAMENTOS</EntityName>
  <Level>Benner</Level>
  <Scripts>
    <ScriptItemPortable>
      <FunctionName>Load</FunctionName>
      <LanguageName>IronPython</LanguageName>
      <SourceCode>def Load(widget):
    widgetContrato = widget.ProviderWidget
    if widgetContrato == None: return
    
    contrato = widgetContrato.Entity
    if contrato == None: return

    widget.Hidden = contrato.VisibilidadeApontamentosEMedicoes()

    if contrato.Status == 3:
        widget.View.Commands["CMD_NOVO"].Visible = True
</SourceCode>
    </ScriptItemPortable>
  </Scripts>
</ScriptPortable>