<?xml version="1.0"?>
<TaskPortable xmlns:xsd="http://www.w3.org/2001/XMLSchema" xmlns:xsi="http://www.w3.org/2001/XMLSchema-instance">
  <Id>ACESSOINICIO_PRODUCAO</Id>
  <Title>Acesso Início - Produção</Title>
  <Description>Concede acesso a página de totalizadores de produção</Description>
  <Level>Benner</Level>
  <Reports />
  <Pages>
    <string>PRODUCAO_INICIO</string>
  </Pages>
  <Components />
  <Apis />
  <Operations>
    <string>EMPRESAS|UPDATE</string>
    <string>EMPRESAS|VIEW</string>
    <string>FILIAIS|UPDATE</string>
    <string>FILIAIS|VIEW</string>
    <string>PR_APONTAMENTOS_PENDENTES.DATASOURCE|VIEW</string>
    <string>PR_ORDENSPRODUCAO_GRAFICO_12MESES.DATASOURCE|VIEW</string>
    <string>PR_ORDENSPRODUCAO_STATUS.DATASOURCE|VIEW</string>
  </Operations>
  <Process />
  <Tasks />
  <FieldVisibility />
</TaskPortable>