<?xml version="1.0"?>
<TaskPortable xmlns:xsd="http://www.w3.org/2001/XMLSchema" xmlns:xsi="http://www.w3.org/2001/XMLSchema-instance">
  <Id>MANTER_CADASTROS_E_PARAMETROS_DE_AQUISICOES</Id>
  <Title>Manter cadastros e parâmetros de aquisições</Title>
  <Level>Benner</Level>
  <Reports />
  <Pages>
    <string>AQUISICOES__LC_OBSERVACAO_ORDEM_COMPRA_FORM</string>
    <string>AQUISICOES__LC_OBSERVACAO_ORDEM_COMPRA_GRID</string>
    <string>AQUISICOES__LC_PARECERTIPOS_FORM</string>
    <string>AQUISICOES__LC_PARECERTIPOS_GRID</string>
    <string>AQUISICOES__MODALIDADESAQUISICAO_FORM</string>
    <string>AQUISICOES__MODALIDADESAQUISICAO_GRID</string>
    <string>AQUISICOES__MODELODOCUMENTOS_FORM</string>
    <string>AQUISICOES__MODELODOCUMENTOS_GRID</string>
    <string>AQUISICOES__TIPOSDEREQUISICAO_FORM</string>
    <string>AQUISICOES__TIPOSDEREQUISICAO_GRID</string>
    <string>LC_CARGA_DE_TIPOS_DE_REQUISICAO__PARAMETROS_FORM</string>
    <string>LC_CARGA_DE_TIPOS_DE_REQUISICAO__REQUISICOES_FORM</string>
    <string>LC_CARGA_DE_TIPOS_DE_REQUISICAO__USUARIOS_FORM</string>
    <string>PARAMETROS_AQUISICOES</string>
  </Pages>
  <Components />
  <Apis />
  <Operations>
    <string>CP_OBSERVACOES|INSERT</string>
    <string>CP_OBSERVACOES|UPDATE</string>
    <string>CP_OBSERVACOES|VIEW</string>
    <string>LC_AQUISICAOMODALIDADES|INSERT</string>
    <string>LC_AQUISICAOMODALIDADES|UPDATE</string>
    <string>LC_AQUISICAOMODALIDADES|VIEW</string>
    <string>LC_DOCUMENTOS|INSERT</string>
    <string>LC_DOCUMENTOS|UPDATE</string>
    <string>LC_DOCUMENTOS|VIEW</string>
    <string>LC_PARECERTIPOS|INSERT</string>
    <string>LC_PARECERTIPOS|UPDATE</string>
    <string>LC_PARECERTIPOS|VIEW</string>
    <string>LC_REQUISICAOANEXOS|INSERT</string>
    <string>LC_REQUISICAOANEXOS|UPDATE</string>
    <string>LC_REQUISICAOANEXOS|VIEW</string>
    <string>LC_REQUISICAOITENS|INSERT</string>
    <string>LC_REQUISICAOITENS|UPDATE</string>
    <string>LC_REQUISICAOITENS|VIEW</string>
    <string>LC_REQUISICAOTIPOALCADAS|INSERT</string>
    <string>LC_REQUISICAOTIPOALCADAS|UPDATE</string>
    <string>LC_REQUISICAOTIPOALCADAS|VIEW</string>
    <string>LC_REQUISICAOTIPOS|INSERT</string>
    <string>LC_REQUISICAOTIPOS|UPDATE</string>
    <string>LC_REQUISICAOTIPOS|VIEW</string>
    <string>LC_REQUISICAOTIPOUSUARIOS|INSERT</string>
    <string>LC_REQUISICAOTIPOUSUARIOS|UPDATE</string>
    <string>LC_REQUISICAOTIPOUSUARIOS|VIEW</string>
    <string>LC_REQUISICOES|INSERT</string>
    <string>LC_REQUISICOES|UPDATE</string>
    <string>LC_REQUISICOES|VIEW</string>
    <string>LC_RETIFICACAOTIPOS|INSERT</string>
    <string>LC_RETIFICACAOTIPOS|UPDATE</string>
    <string>LC_RETIFICACAOTIPOS|VIEW</string>
  </Operations>
  <Process />
  <Tasks />
  <FieldVisibility />
</TaskPortable>