<?xml version="1.0"?>
<TaskPortable xmlns:xsd="http://www.w3.org/2001/XMLSchema" xmlns:xsi="http://www.w3.org/2001/XMLSchema-instance">
  <Id>MANTER_FXLANCGRUPOSLANCAMENTO</Id>
  <Title>Manter Lançamentos Grupos de Lançamento</Title>
  <Level>Benner</Level>
  <Reports />
  <Pages>
    <string>FXLANCAMENTORAPIDOFORM</string>
    <string>FXLANCAMENTORAPIDOGRID</string>
    <string>PAGES_FXGRUPOSLANCAMENTO_FORM</string>
    <string>PAGES_FXGRUPOSLANCAMENTO_GRID</string>
  </Pages>
  <Components />
  <Apis />
  <Operations>
    <string>FX_GRUPOSLANCAMENTO|INSERT</string>
    <string>FX_GRUPOSLANCAMENTO|UPDATE</string>
    <string>FX_GRUPOSLANCAMENTO|VIEW</string>
    <string>FX_LANCAMENTORAPIDO|INSERT</string>
    <string>FX_LANCAMENTORAPIDO|UPDATE</string>
    <string>FX_LANCAMENTORAPIDO|VIEW</string>
  </Operations>
  <Process />
  <Tasks />
  <FieldVisibility />
</TaskPortable>