<?xml version="1.0"?>
<TaskPortable xmlns:xsd="http://www.w3.org/2001/XMLSchema" xmlns:xsi="http://www.w3.org/2001/XMLSchema-instance">
  <Id>MANTER_FAMILIASITEM</Id>
  <Title>Manter Famílias de item</Title>
  <Level>Benner</Level>
  <Reports />
  <Pages>
    <string>CARGA_DE_PRODUTOS__FAMILIAS__CLIENTES_FORM</string>
    <string>CARGA_DE_PRODUTOS__FAMILIAS__FAMILIA_CODIGOS_ATIVIDADE_FORM</string>
    <string>CARGA_DE_PRODUTOS__FAMILIAS__ITENS_DA_EMPRESA_FORM</string>
    <string>CARGA_DE_PRODUTOS__FAMILIAS__POLITICAS_COMERCIAIS_FORM</string>
    <string>CARGA_DE_PRODUTOS__FAMILIAS__TIPODEDOCUMENTOS_FORM</string>
    <string>CARGA_DE_PRODUTOS__FAMILIAS__TIPOS_DE_VARIACAO_DA_FAMILIA_FORM</string>
    <string>CARGA_DE_PRODUTOS__FILIAIS__SUBSTITUTOS_FORM</string>
    <string>COMERCIAL_CONFIGURACOESCOMERCIAIS__FAMILIAS_DE_ITENS_FORM</string>
    <string>COMERCIAL_CONFIGURACOESCOMERCIAIS__FAMILIAS_DE_ITENS_GRID</string>
    <string>MATERIAIS__FAMILIAS_DE_ITEM_FORM</string>
    <string>MATERIAIS__FAMILIAS_DE_ITEM_GRID</string>
    <string>MATERIAIS_GERARCLIENTES</string>
    <string>MATERIAIS_GERARFORNECEDORES</string>
  </Pages>
  <Components>
    <string>Benner.Corporativo.Definicoes.Materiais.Interfaces.IGerarClientesServices|GERARPESSOASPORBTL</string>
    <string>Benner.Corporativo.Definicoes.Materiais.Interfaces.IGerarFornecedoresServices|GERARPESSOASPORBTL</string>
    <string>Benner.Corporativo.Legacy.ERPProxy.ErpEnvironment|SQLDATE</string>
    <string>Benner.Corporativo.Materiais.Legacy.LegacyInterface|GERARCODIGOREFERENCIA</string>
  </Components>
  <Apis />
  <Operations>
    <string>GN_DOCUMENTOHABILITACAOITEM|INSERT</string>
    <string>GN_DOCUMENTOHABILITACAOITEM|UPDATE</string>
    <string>GN_DOCUMENTOHABILITACAOITEM|VIEW</string>
    <string>GN_PESSOAS|INSERT</string>
    <string>GN_PESSOAS|UPDATE</string>
    <string>GN_POLITICASCOMERCIAIS|INSERT</string>
    <string>GN_POLITICASCOMERCIAIS|UPDATE</string>
    <string>PD_FAMILIACODIGOATIVIDADE|INSERT</string>
    <string>PD_FAMILIACODIGOATIVIDADE|UPDATE</string>
    <string>PD_FAMILIASPRODUTOS|AJUSTARCUSTOMEDIO</string>
    <string>PD_FAMILIASPRODUTOS|BOTAOFORNECEDORES</string>
    <string>PD_FAMILIASPRODUTOS|COPIARCOMPRADORPARAITENS</string>
    <string>PD_FAMILIASPRODUTOS|COPIARCOMPRADORPARANIVEISABAIXO</string>
    <string>PD_FAMILIASPRODUTOS|INSERT</string>
    <string>PD_FAMILIASPRODUTOS|UPDATE</string>
    <string>PD_FAMILIASPRODUTOS|VIEW</string>
    <string>PD_FAMILIATIPOSVARIACAO|INSERT</string>
    <string>PD_FAMILIATIPOSVARIACAO|UPDATE</string>
    <string>PD_PRODUTOSPAI|INSERT</string>
    <string>PD_PRODUTOSPAI|UPDATE</string>
    <string>PD_VARIACAOCLIENTES|INSERT</string>
    <string>PD_VARIACAOCLIENTES|UPDATE</string>
    <string>PD_VARIACAOFORNECEDORES|INSERT</string>
    <string>PD_VARIACAOFORNECEDORES|UPDATE</string>
  </Operations>
  <Process />
  <Tasks />
  <FieldVisibility />
</TaskPortable>