<?xml version="1.0"?>
<TaskPortable xmlns:xsd="http://www.w3.org/2001/XMLSchema" xmlns:xsi="http://www.w3.org/2001/XMLSchema-instance">
  <Id>VISUALIZAR_TRIBUTOS_FORM_CONSULTA_LANCAMENTOS</Id>
  <Title>Visualizar formulário de consulta em apenas visualização dos lançamentos</Title>
  <Level>Benner</Level>
  <Reports />
  <Pages>
    <string>TRIBUTOS_OPERACOESFISCAIS</string>
    <string>TRIBUTOS_OPERACOESFISCAIS_LANCAMENTOS</string>
  </Pages>
  <Components />
  <Apis />
  <Operations>
    <string>TR_PCOPERACOESFISCAIS|VIEW</string>
  </Operations>
  <Process />
  <Tasks />
  <FieldVisibility />
</TaskPortable>