<?xml version="1.0"?>
<TaskPortable xmlns:xsd="http://www.w3.org/2001/XMLSchema" xmlns:xsi="http://www.w3.org/2001/XMLSchema-instance">
  <Id>VISUALIZAR_CADASTROS_PROJETOS</Id>
  <Title>Visualizar cadastros projetos</Title>
  <Description>Visualizar cadastros do módulo projetos</Description>
  <Level>Benner</Level>
  <Reports />
  <Pages>
    <string>CADASTRO_PORTFOLIO</string>
    <string>GESTAO_PROJETOS</string>
    <string>MODULO_GESTAO_PROJETOS</string>
    <string>PORTFOLIO_PROJETOS</string>
    <string>PROJETOS_CADASTRO_CATEGORIA</string>
    <string>PROJETOS_CADASTRO_CATEGORIAS</string>
    <string>PROJETOS_CADASTRO_TIPO</string>
    <string>PROJETOS_CADASTRO_TIPOS</string>
  </Pages>
  <Components />
  <Apis />
  <Operations>
    <string>GP_CATEGORIASPROJETOS|VIEW</string>
    <string>GP_PORTFOLIOS|VIEW</string>
    <string>GP_TIPOSPROJETOS|VIEW</string>
  </Operations>
  <Process />
  <Tasks />
  <FieldVisibility />
</TaskPortable>