<?xml version="1.0"?>
<TaskPortable xmlns:xsd="http://www.w3.org/2001/XMLSchema" xmlns:xsi="http://www.w3.org/2001/XMLSchema-instance">
  <Id>VISUALIZAR_NECESSIDADE_LIQUIDA</Id>
  <Title>Visualizar Necessidade Liquida</Title>
  <Level>Benner</Level>
  <Reports />
  <Pages>
    <string>AGA_A_PRODUCAO_NECESSIDADELIQUIDA_FORM</string>
    <string>AGA_A_PRODUCAO_NECESSIDADELIQUIDA_GRID</string>
    <string>AGA_A_PRODUCAO_NECESSIDADELIQUIDA_INSERIRPRODUTOSOV</string>
    <string>AGA_A_PRODUCAO_NECESSIDADELIQUIDA_ITENSNECESSIDADE_FORM</string>
    <string>AGA_A_PRODUCAO_RESULTADOCALCULONECESSIDADELIQUIDA_RESULTADOCALCULO</string>
    <string>NECESSIDADELIQUIDA_DOCUMENTOSAGERAR</string>
    <string>NECESSIDADELIQUIDA_ORDENSEXISTENTES</string>
    <string>PD_SALDOS_ESTOQUE</string>
    <string>PRODUCAO_RESULTADOCALCULOS</string>
  </Pages>
  <Components />
  <Apis />
  <Operations>
    <string>CP_ORDENSCOMPRAENTREGA|VIEW</string>
    <string>CP_REQUISICOES|VIEW</string>
    <string>CP_REQUISICOESPAI|VIEW</string>
    <string>MRP_NECESSIDADES|VIEW</string>
    <string>PR_NECESSIDADELIQUIDA|VIEW</string>
    <string>PR_NECESSIDADELIQUIDACALCGERAL|VIEW</string>
    <string>PR_NECESSIDADELIQUIDAITENS|VIEW</string>
    <string>PR_NECLIQRESULTCALCINSUMOS|VIEW</string>
    <string>PR_NECLIQRESULTCALCMANUFATURAD|VIEW</string>
    <string>PR_ORDENSPRODUCAO|VIEW</string>
  </Operations>
  <Process />
  <Tasks />
  <FieldVisibility />
</TaskPortable>